[
  {
    "personid": 1,
    "firstname": "Iman Singh",
    "lastname": "Kunwar",
    "gender": "Male",
    "dateofbirth": "1930-06-10",
    "dateofdeath": null,
    "maternalfamilyid": null,
    "paternalfamilyid": null,
    "occupation": "Teacher"
  },
  {
    "personid": 2,
    "firstname": "Hira Kumari",
    "lastname": "Kunwar",
    "gender": "Female",
    "dateofbirth": "1935-06-10",
    "dateofdeath": null,
    "maternalfamilyid": null,
    "paternalfamilyid": null,
    "occupation": "Housewife"
  },
  {
    "personid": 3,
    "firstname": "Saraswati",
    "lastname": "Kunwar",
    "gender": "Female",
    "dateofbirth": "1960-06-10",
    "dateofdeath": null,
    "maternalfamilyid": null,
    "paternalfamilyid": null,
    "occupation": "Nurse"
  },
  {
    "personid": 4,
    "firstname": "Dhurba",
    "lastname": "Kunwar",
    "gender": "Male",
    "dateofbirth": "1960-06-10",
    "dateofdeath": null,
    "maternalfamilyid": null,
    "paternalfamilyid": null,
    "occupation": "Officer"
  },
  {
    "personid": 5,
    "firstname": "Mina",
    "lastname": "Kunwar",
    "gender": "Female",
    "dateofbirth": "1960-06-10",
    "dateofdeath": null,
    "maternalfamilyid": null,
    "paternalfamilyid": null,
    "occupation": "Teacher"
  },
  {
    "personid": 6,
    "firstname": "Kirtan",
    "lastname": "Kunwar",
    "gender": "Male",
    "dateofbirth": "2004-05-31",
    "dateofdeath": null,
    "maternalfamilyid": null,
    "paternalfamilyid": null,
    "occupation": "Student"
  },
  {
    "personid": 7,
    "firstname": "Senjougahara",
    "lastname": "Hitagi",
    "gender": "Female",
    "dateofbirth": "1999-06-07",
    "dateofdeath": null,
    "maternalfamilyid": null,
    "paternalfamilyid": null,
    "occupation": "Student"
  },

  {
    "personid": 8,
    "firstname": "Namchhuwachha",
    "lastname": "Kirati",
    "gender": "Male",
    "dateofbirth": "1982-01-07",
    "dateofdeath": null,
    "maternalfamilyid": null,
    "paternalfamilyid": null,
    "occupation": "Businessman"
  },
  {
    "personid": 9,
    "firstname": "Sharada",
    "lastname": "Rai",
    "gender": "Female",
    "dateofbirth": "1984-03-10",
    "dateofdeath": null,
    "maternalfamilyid": null,
    "paternalfamilyid": null,
    "occupation": "Housewife"
  },
  {
    "personid": 10,
    "firstname": "Sita",
    "lastname": "Rai",
    "gender": "Female",
    "dateofbirth": "1935-06-10",
    "dateofdeath": null,
    "maternalfamilyid": null,
    "paternalfamilyid": null,
    "occupation": "Housewife"
  },
  {
    "personid": 11,
    "firstname": "Kripa",
    "lastname": "Kirati",
    "gender": "Male",
    "dateofbirth": "1932-08-17",
    "dateofdeath": null,
    "maternalfamilyid": null,
    "paternalfamilyid": null,
    "occupation": "Government Officer"
  },
  {
    "personid": 12,
    "firstname": "Chawa Chha",
    "lastname": "Kirati",
    "gender": "Male",
    "dateofbirth": "1984-09-20",
    "dateofdeath": null,
    "maternalfamilyid": null,
    "paternalfamilyid": null,
    "occupation": "Teacher"
  },
  {
    "personid": 13,
    "firstname": "Asha",
    "lastname": "Rai",
    "gender": "Female",
    "dateofbirth": "1986-04-02",
    "dateofdeath": null,
    "maternalfamilyid": null,
    "paternalfamilyid": null,
    "occupation": "Housewife"
  },
  {
    "personid": 14,
    "firstname": "Tayama",
    "lastname": "Kirati",
    "gender": "Female",
    "dateofbirth": "2003-01-27",
    "dateofdeath": null,
    "maternalfamilyid": null,
    "paternalfamilyid": null,
    "occupation": "Student"
  },
  {
    "personid": 15,
    "firstname": "Henkubung",
    "lastname": "Kirati",
    "gender": "Male",
    "dateofbirth": "2015-06-17",
    "dateofdeath": null,
    "maternalfamilyid": null,
    "paternalfamilyid": null,
    "occupation": "Student"
  }
]
